{
  "manager_id": "FPA",
  "holdings": [
    {
      "symbol": "GOOGL",
      "company_name": "Alphabet Inc.",
      "manager_id": "FPA",
      "shares": 1911429,
      "value": 598277000,
      "percentage": 8.03,
      "portfolio_percent": 8.03,
      "reported_price": 313.0,
      "current_price": 384.8,
      "price_change_percent": 0.0,
      "recent_activity": "Reduce 21.09%",
      "week_52_low": 147.33,
      "week_52_high": 385.84,
      "reporting_date": "",
      "reporting_quarter": "Q2 2026",
      "market_cap": 0.0,
      "pe_ratio": 0.0,
      "dividend_yield": 0.0,
      "price_to_book": 0.0,
      "sector": "",
      "industry": "",
      "data_quality": "Low"
    },
    {
      "symbol": "ADI",
      "company_name": "Analog Devices",
      "manager_id": "FPA",
      "shares": 1874867,
      "value": 508464000,
      "percentage": 6.82,
      "portfolio_percent": 6.82,
      "reported_price": 271.2,
      "current_price": 402.26,
      "price_change_percent": 0.0,
      "recent_activity": "Reduce 6.03%",
      "week_52_low": 190.53,
      "week_52_high": 408.37,
      "reporting_date": "",
      "reporting_quarter": "Q2 2026",
      "market_cap": 0.0,
      "pe_ratio": 0.0,
      "dividend_yield": 0.0,
      "price_to_book": 0.0,
      "sector": "",
      "industry": "",
      "data_quality": "Low"
    },
    {
      "symbol": "META",
      "company_name": "Meta Platforms Inc.",
      "manager_id": "FPA",
      "shares": 702121,
      "value": 463463000,
      "percentage": 6.22,
      "portfolio_percent": 6.22,
      "reported_price": 660.09,
      "current_price": 611.91,
      "price_change_percent": 0.0,
      "recent_activity": "Reduce 1.25%",
      "week_52_low": 520.26,
      "week_52_high": 794.38,
      "reporting_date": "",
      "reporting_quarter": "Q2 2026",
      "market_cap": 0.0,
      "pe_ratio": 0.0,
      "dividend_yield": 0.0,
      "price_to_book": 0.0,
      "sector": "",
      "industry": "",
      "data_quality": "Low"
    },
    {
      "symbol": "GOOG",
      "company_name": "Alphabet Inc. CL C",
      "manager_id": "FPA",
      "shares": 1349592,
      "value": 423502000,
      "percentage": 5.68,
      "portfolio_percent": 5.68,
      "reported_price": 313.8,
      "current_price": 381.94,
      "price_change_percent": 0.0,
      "recent_activity": "Reduce 9.04%",
      "week_52_low": 148.98,
      "week_52_high": 382.63,
      "reporting_date": "",
      "reporting_quarter": "Q2 2026",
      "market_cap": 0.0,
      "pe_ratio": 0.0,
      "dividend_yield": 0.0,
      "price_to_book": 0.0,
      "sector": "",
      "industry": "",
      "data_quality": "Low"
    },
    {
      "symbol": "C",
      "company_name": "Citigroup Inc.",
      "manager_id": "FPA",
      "shares": 3506931,
      "value": 409224000,
      "percentage": 5.49,
      "portfolio_percent": 5.49,
      "reported_price": 116.69,
      "current_price": 127.98,
      "price_change_percent": 0.0,
      "recent_activity": "Reduce 7.20%",
      "week_52_low": 66.17,
      "week_52_high": 135.29,
      "reporting_date": "",
      "reporting_quarter": "Q2 2026",
      "market_cap": 0.0,
      "pe_ratio": 0.0,
      "dividend_yield": 0.0,
      "price_to_book": 0.0,
      "sector": "",
      "industry": "",
      "data_quality": "Low"
    },
    {
      "symbol": "TEL",
      "company_name": "TE Connectivity plc",
      "manager_id": "FPA",
      "shares": 1779970,
      "value": 404961000,
      "percentage": 5.43,
      "portfolio_percent": 5.43,
      "reported_price": 227.51,
      "current_price": 211.66,
      "price_change_percent": 0.0,
      "recent_activity": "Reduce 16.01%",
      "week_52_low": 144.08,
      "week_52_high": 252.56,
      "reporting_date": "",
      "reporting_quarter": "Q2 2026",
      "market_cap": 0.0,
      "pe_ratio": 0.0,
      "dividend_yield": 0.0,
      "price_to_book": 0.0,
      "sector": "",
      "industry": "",
      "data_quality": "Low"
    },
    {
      "symbol": "BDX",
      "company_name": "Becton Dickinson",
      "manager_id": "FPA",
      "shares": 1951246,
      "value": 378678000,
      "percentage": 5.08,
      "portfolio_percent": 5.08,
      "reported_price": 194.07,
      "current_price": 149.04,
      "price_change_percent": 0.0,
      "recent_activity": "Add 108.41%",
      "week_52_low": 125.44,
      "week_52_high": 186.16,
      "reporting_date": "",
      "reporting_quarter": "Q2 2026",
      "market_cap": 0.0,
      "pe_ratio": 0.0,
      "dividend_yield": 0.0,
      "price_to_book": 0.0,
      "sector": "",
      "industry": "",
      "data_quality": "Low"
    },
    {
      "symbol": "IFF",
      "company_name": "International Flavors & Fragrances Inc.",
      "manager_id": "FPA",
      "shares": 5326041,
      "value": 358922000,
      "percentage": 4.81,
      "portfolio_percent": 4.81,
      "reported_price": 67.39,
      "current_price": 70.2,
      "price_change_percent": 0.0,
      "recent_activity": "Add 8.61%",
      "week_52_low": 58.43,
      "week_52_high": 83.95,
      "reporting_date": "",
      "reporting_quarter": "Q2 2026",
      "market_cap": 0.0,
      "pe_ratio": 0.0,
      "dividend_yield": 0.0,
      "price_to_book": 0.0,
      "sector": "",
      "industry": "",
      "data_quality": "Low"
    },
    {
      "symbol": "AMZN",
      "company_name": "Amazon.com Inc.",
      "manager_id": "FPA",
      "shares": 1411199,
      "value": 325733000,
      "percentage": 4.37,
      "portfolio_percent": 4.37,
      "reported_price": 230.82,
      "current_price": 265.06,
      "price_change_percent": 0.0,
      "recent_activity": "Reduce 1.75%",
      "week_52_low": 183.85,
      "week_52_high": 273.88,
      "reporting_date": "",
      "reporting_quarter": "Q2 2026",
      "market_cap": 0.0,
      "pe_ratio": 0.0,
      "dividend_yield": 0.0,
      "price_to_book": 0.0,
      "sector": "",
      "industry": "",
      "data_quality": "Low"
    },
    {
      "symbol": "CMCSA",
      "company_name": "Comcast Corp.",
      "manager_id": "FPA",
      "shares": 8399831,
      "value": 251071000,
      "percentage": 3.37,
      "portfolio_percent": 3.37,
      "reported_price": 29.89,
      "current_price": 27.04,
      "price_change_percent": 0.0,
      "recent_activity": "Reduce 25.26%",
      "week_52_low": 23.62,
      "week_52_high": 33.03,
      "reporting_date": "",
      "reporting_quarter": "Q2 2026",
      "market_cap": 0.0,
      "pe_ratio": 0.0,
      "dividend_yield": 0.0,
      "price_to_book": 0.0,
      "sector": "",
      "industry": "",
      "data_quality": "Low"
    },
    {
      "symbol": "AON",
      "company_name": "Aon Plc",
      "manager_id": "FPA",
      "shares": 656531,
      "value": 231677000,
      "percentage": 3.11,
      "portfolio_percent": 3.11,
      "reported_price": 352.88,
      "current_price": 311.65,
      "price_change_percent": 0.0,
      "recent_activity": "Add 0.32%",
      "week_52_low": 304.59,
      "week_52_high": 378.56,
      "reporting_date": "",
      "reporting_quarter": "Q2 2026",
      "market_cap": 0.0,
      "pe_ratio": 0.0,
      "dividend_yield": 0.0,
      "price_to_book": 0.0,
      "sector": "",
      "industry": "",
      "data_quality": "Low"
    },
    {
      "symbol": "FERG",
      "company_name": "Ferguson Enterprises Inc.",
      "manager_id": "FPA",
      "shares": 887120,
      "value": 197500000,
      "percentage": 2.65,
      "portfolio_percent": 2.65,
      "reported_price": 222.63,
      "current_price": 267.71,
      "price_change_percent": 0.0,
      "recent_activity": "Reduce 3.19%",
      "week_52_low": 163.52,
      "week_52_high": 270.63,
      "reporting_date": "",
      "reporting_quarter": "Q2 2026",
      "market_cap": 0.0,
      "pe_ratio": 0.0,
      "dividend_yield": 0.0,
      "price_to_book": 0.0,
      "sector": "",
      "industry": "",
      "data_quality": "Low"
    },
    {
      "symbol": "AMRZ",
      "company_name": "Amrize Ltd",
      "manager_id": "FPA",
      "shares": 3408072,
      "value": 184309000,
      "percentage": 2.47,
      "portfolio_percent": 2.47,
      "reported_price": 54.08,
      "current_price": 53.78,
      "price_change_percent": 0.0,
      "recent_activity": "Buy",
      "week_52_low": 43.78,
      "week_52_high": 65.43,
      "reporting_date": "",
      "reporting_quarter": "Q2 2026",
      "market_cap": 0.0,
      "pe_ratio": 0.0,
      "dividend_yield": 0.0,
      "price_to_book": 0.0,
      "sector": "",
      "industry": "",
      "data_quality": "Low"
    },
    {
      "symbol": "ICLR",
      "company_name": "ICON plc",
      "manager_id": "FPA",
      "shares": 980804,
      "value": 178722000,
      "percentage": 2.4,
      "portfolio_percent": 2.4,
      "reported_price": 182.22,
      "current_price": 118.33,
      "price_change_percent": 0.0,
      "recent_activity": "Add 0.66%",
      "week_52_low": 66.57,
      "week_52_high": 211.0,
      "reporting_date": "",
      "reporting_quarter": "Q2 2026",
      "market_cap": 0.0,
      "pe_ratio": 0.0,
      "dividend_yield": 0.0,
      "price_to_book": 0.0,
      "sector": "",
      "industry": "",
      "data_quality": "Low"
    },
    {
      "symbol": "FBIN",
      "company_name": "Fortune Brands Innovations Inc.",
      "manager_id": "FPA",
      "shares": 3524498,
      "value": 176295000,
      "percentage": 2.36,
      "portfolio_percent": 2.36,
      "reported_price": 50.02,
      "current_price": 40.54,
      "price_change_percent": 0.0,
      "recent_activity": "Add 22.97%",
      "week_52_low": 36.07,
      "week_52_high": 64.53,
      "reporting_date": "",
      "reporting_quarter": "Q2 2026",
      "market_cap": 0.0,
      "pe_ratio": 0.0,
      "dividend_yield": 0.0,
      "price_to_book": 0.0,
      "sector": "",
      "industry": "",
      "data_quality": "Low"
    },
    {
      "symbol": "NXPI",
      "company_name": "NXP Semiconductors NV",
      "manager_id": "FPA",
      "shares": 766330,
      "value": 166340000,
      "percentage": 2.23,
      "portfolio_percent": 2.23,
      "reported_price": 217.06,
      "current_price": 293.59,
      "price_change_percent": 0.0,
      "recent_activity": "Add 0.17%",
      "week_52_low": 177.25,
      "week_52_high": 294.34,
      "reporting_date": "",
      "reporting_quarter": "Q2 2026",
      "market_cap": 0.0,
      "pe_ratio": 0.0,
      "dividend_yield": 0.0,
      "price_to_book": 0.0,
      "sector": "",
      "industry": "",
      "data_quality": "Low"
    },
    {
      "symbol": "JEF",
      "company_name": "Jefferies Financial Group Inc.",
      "manager_id": "FPA",
      "shares": 2580283,
      "value": 159900000,
      "percentage": 2.14,
      "portfolio_percent": 2.14,
      "reported_price": 61.97,
      "current_price": 48.22,
      "price_change_percent": 0.0,
      "recent_activity": "",
      "week_52_low": 35.53,
      "week_52_high": 70.0,
      "reporting_date": "",
      "reporting_quarter": "Q2 2026",
      "market_cap": 0.0,
      "pe_ratio": 0.0,
      "dividend_yield": 0.0,
      "price_to_book": 0.0,
      "sector": "",
      "industry": "",
      "data_quality": "Low"
    },
    {
      "symbol": "MTN",
      "company_name": "Vail Resorts Inc.",
      "manager_id": "FPA",
      "shares": 1087702,
      "value": 144447000,
      "percentage": 1.94,
      "portfolio_percent": 1.94,
      "reported_price": 132.8,
      "current_price": 127.18,
      "price_change_percent": 0.0,
      "recent_activity": "Add 7.38%",
      "week_52_low": 118.51,
      "week_52_high": 164.98,
      "reporting_date": "",
      "reporting_quarter": "Q2 2026",
      "market_cap": 0.0,
      "pe_ratio": 0.0,
      "dividend_yield": 0.0,
      "price_to_book": 0.0,
      "sector": "",
      "industry": "",
      "data_quality": "Low"
    },
    {
      "symbol": "LPLA",
      "company_name": "LPL Financial Holdings Inc.",
      "manager_id": "FPA",
      "shares": 387412,
      "value": 138372000,
      "percentage": 1.86,
      "portfolio_percent": 1.86,
      "reported_price": 357.17,
      "current_price": 334.13,
      "price_change_percent": 0.0,
      "recent_activity": "Reduce 12.65%",
      "week_52_low": 281.51,
      "week_52_high": 402.53,
      "reporting_date": "",
      "reporting_quarter": "Q2 2026",
      "market_cap": 0.0,
      "pe_ratio": 0.0,
      "dividend_yield": 0.0,
      "price_to_book": 0.0,
      "sector": "",
      "industry": "",
      "data_quality": "Low"
    },
    {
      "symbol": "LBRDK",
      "company_name": "Liberty Broadband Corp. CL C",
      "manager_id": "FPA",
      "shares": 2669348,
      "value": 129730000,
      "percentage": 1.74,
      "portfolio_percent": 1.74,
      "reported_price": 48.6,
      "current_price": 38.49,
      "price_change_percent": 0.0,
      "recent_activity": "Buy",
      "week_52_low": 36.6,
      "week_52_high": 97.16,
      "reporting_date": "",
      "reporting_quarter": "Q2 2026",
      "market_cap": 0.0,
      "pe_ratio": 0.0,
      "dividend_yield": 0.0,
      "price_to_book": 0.0,
      "sector": "",
      "industry": "",
      "data_quality": "Low"
    },
    {
      "symbol": "NOV",
      "company_name": "Nov Inc.",
      "manager_id": "FPA",
      "shares": 8093810,
      "value": 126506000,
      "percentage": 1.7,
      "portfolio_percent": 1.7,
      "reported_price": 15.63,
      "current_price": 20.46,
      "price_change_percent": 0.0,
      "recent_activity": "Add 1.85%",
      "week_52_low": 11.11,
      "week_52_high": 20.93,
      "reporting_date": "",
      "reporting_quarter": "Q2 2026",
      "market_cap": 0.0,
      "pe_ratio": 0.0,
      "dividend_yield": 0.0,
      "price_to_book": 0.0,
      "sector": "",
      "industry": "",
      "data_quality": "Low"
    },
    {
      "symbol": "TMO",
      "company_name": "Thermo Fisher Scientific",
      "manager_id": "FPA",
      "shares": 218572,
      "value": 126652000,
      "percentage": 1.7,
      "portfolio_percent": 1.7,
      "reported_price": 579.45,
      "current_price": 478.96,
      "price_change_percent": 0.0,
      "recent_activity": "Add 1.69%",
      "week_52_low": 384.44,
      "week_52_high": 643.35,
      "reporting_date": "",
      "reporting_quarter": "Q2 2026",
      "market_cap": 0.0,
      "pe_ratio": 0.0,
      "dividend_yield": 0.0,
      "price_to_book": 0.0,
      "sector": "",
      "industry": "",
      "data_quality": "Low"
    },
    {
      "symbol": "BIO",
      "company_name": "Bio-Rad Laboratories Inc.",
      "manager_id": "FPA",
      "shares": 401457,
      "value": 121637000,
      "percentage": 1.63,
      "portfolio_percent": 1.63,
      "reported_price": 302.99,
      "current_price": 280.12,
      "price_change_percent": 0.0,
      "recent_activity": "Add 1.79%",
      "week_52_low": 211.43,
      "week_52_high": 343.12,
      "reporting_date": "",
      "reporting_quarter": "Q2 2026",
      "market_cap": 0.0,
      "pe_ratio": 0.0,
      "dividend_yield": 0.0,
      "price_to_book": 0.0,
      "sector": "",
      "industry": "",
      "data_quality": "Low"
    },
    {
      "symbol": "MAR",
      "company_name": "Marriott Int'l.",
      "manager_id": "FPA",
      "shares": 389857,
      "value": 120949000,
      "percentage": 1.62,
      "portfolio_percent": 1.62,
      "reported_price": 310.24,
      "current_price": 361.69,
      "price_change_percent": 0.0,
      "recent_activity": "Reduce 13.51%",
      "week_52_low": 238.11,
      "week_52_high": 380.0,
      "reporting_date": "",
      "reporting_quarter": "Q2 2026",
      "market_cap": 0.0,
      "pe_ratio": 0.0,
      "dividend_yield": 0.0,
      "price_to_book": 0.0,
      "sector": "",
      "industry": "",
      "data_quality": "Low"
    },
    {
      "symbol": "KMX",
      "company_name": "CarMax Inc.",
      "manager_id": "FPA",
      "shares": 2924081,
      "value": 112986000,
      "percentage": 1.52,
      "portfolio_percent": 1.52,
      "reported_price": 38.64,
      "current_price": 39.31,
      "price_change_percent": 0.0,
      "recent_activity": "Add 17.84%",
      "week_52_low": 30.26,
      "week_52_high": 71.99,
      "reporting_date": "",
      "reporting_quarter": "Q2 2026",
      "market_cap": 0.0,
      "pe_ratio": 0.0,
      "dividend_yield": 0.0,
      "price_to_book": 0.0,
      "sector": "",
      "industry": "",
      "data_quality": "Low"
    },
    {
      "symbol": "KMI",
      "company_name": "Kinder Morgan",
      "manager_id": "FPA",
      "shares": 4076504,
      "value": 112063000,
      "percentage": 1.5,
      "portfolio_percent": 1.5,
      "reported_price": 27.49,
      "current_price": 32.87,
      "price_change_percent": 0.0,
      "recent_activity": "Add 1.83%",
      "week_52_low": 25.2,
      "week_52_high": 34.73,
      "reporting_date": "",
      "reporting_quarter": "Q2 2026",
      "market_cap": 0.0,
      "pe_ratio": 0.0,
      "dividend_yield": 0.0,
      "price_to_book": 0.0,
      "sector": "",
      "industry": "",
      "data_quality": "Low"
    },
    {
      "symbol": "WFC",
      "company_name": "Wells Fargo",
      "manager_id": "FPA",
      "shares": 1109828,
      "value": 103436000,
      "percentage": 1.39,
      "portfolio_percent": 1.39,
      "reported_price": 93.2,
      "current_price": 82.23,
      "price_change_percent": 0.0,
      "recent_activity": "Reduce 14.08%",
      "week_52_low": 68.93,
      "week_52_high": 97.28,
      "reporting_date": "",
      "reporting_quarter": "Q2 2026",
      "market_cap": 0.0,
      "pe_ratio": 0.0,
      "dividend_yield": 0.0,
      "price_to_book": 0.0,
      "sector": "",
      "industry": "",
      "data_quality": "Low"
    },
    {
      "symbol": "CHTR",
      "company_name": "Charter Communications",
      "manager_id": "FPA",
      "shares": 461525,
      "value": 96343000,
      "percentage": 1.29,
      "portfolio_percent": 1.29,
      "reported_price": 208.75,
      "current_price": 165.17,
      "price_change_percent": 0.0,
      "recent_activity": "Reduce 28.57%",
      "week_52_low": 158.0,
      "week_52_high": 437.06,
      "reporting_date": "",
      "reporting_quarter": "Q2 2026",
      "market_cap": 0.0,
      "pe_ratio": 0.0,
      "dividend_yield": 0.0,
      "price_to_book": 0.0,
      "sector": "",
      "industry": "",
      "data_quality": "Low"
    },
    {
      "symbol": "WAB",
      "company_name": "WABTEC Corp.",
      "manager_id": "FPA",
      "shares": 444548,
      "value": 94889000,
      "percentage": 1.27,
      "portfolio_percent": 1.27,
      "reported_price": 213.45,
      "current_price": 269.89,
      "price_change_percent": 0.0,
      "recent_activity": "Add 1.81%",
      "week_52_low": 183.07,
      "week_52_high": 275.84,
      "reporting_date": "",
      "reporting_quarter": "Q2 2026",
      "market_cap": 0.0,
      "pe_ratio": 0.0,
      "dividend_yield": 0.0,
      "price_to_book": 0.0,
      "sector": "",
      "industry": "",
      "data_quality": "Low"
    },
    {
      "symbol": "NATL",
      "company_name": "NCR Atleos Corp.",
      "manager_id": "FPA",
      "shares": 2040700,
      "value": 77771000,
      "percentage": 1.04,
      "portfolio_percent": 1.04,
      "reported_price": 38.11,
      "current_price": 44.38,
      "price_change_percent": 0.0,
      "recent_activity": "",
      "week_52_low": 23.56,
      "week_52_high": 48.5,
      "reporting_date": "",
      "reporting_quarter": "Q2 2026",
      "market_cap": 0.0,
      "pe_ratio": 0.0,
      "dividend_yield": 0.0,
      "price_to_book": 0.0,
      "sector": "",
      "industry": "",
      "data_quality": "Low"
    },
    {
      "symbol": "UBER",
      "company_name": "Uber Technologies Inc.",
      "manager_id": "FPA",
      "shares": 953263,
      "value": 77891000,
      "percentage": 1.04,
      "portfolio_percent": 1.04,
      "reported_price": 81.71,
      "current_price": 74.61,
      "price_change_percent": 0.0,
      "recent_activity": "Add 1.96%",
      "week_52_low": 68.46,
      "week_52_high": 101.99,
      "reporting_date": "",
      "reporting_quarter": "Q2 2026",
      "market_cap": 0.0,
      "pe_ratio": 0.0,
      "dividend_yield": 0.0,
      "price_to_book": 0.0,
      "sector": "",
      "industry": "",
      "data_quality": "Low"
    },
    {
      "symbol": "DEI",
      "company_name": "Douglas Emmett Inc.",
      "manager_id": "FPA",
      "shares": 6528956,
      "value": 71753000,
      "percentage": 0.96,
      "portfolio_percent": 0.96,
      "reported_price": 10.99,
      "current_price": 10.81,
      "price_change_percent": 0.0,
      "recent_activity": "Add 22.40%",
      "week_52_low": 8.93,
      "week_52_high": 16.16,
      "reporting_date": "",
      "reporting_quarter": "Q2 2026",
      "market_cap": 0.0,
      "pe_ratio": 0.0,
      "dividend_yield": 0.0,
      "price_to_book": 0.0,
      "sector": "",
      "industry": "",
      "data_quality": "Low"
    },
    {
      "symbol": "VNO",
      "company_name": "Vornado Realty Trust",
      "manager_id": "FPA",
      "shares": 1676513,
      "value": 55794000,
      "percentage": 0.75,
      "portfolio_percent": 0.75,
      "reported_price": 33.28,
      "current_price": 29.89,
      "price_change_percent": 0.0,
      "recent_activity": "",
      "week_52_low": 24.57,
      "week_52_high": 42.43,
      "reporting_date": "",
      "reporting_quarter": "Q2 2026",
      "market_cap": 0.0,
      "pe_ratio": 0.0,
      "dividend_yield": 0.0,
      "price_to_book": 0.0,
      "sector": "",
      "industry": "",
      "data_quality": "Low"
    },
    {
      "symbol": "VYX",
      "company_name": "NCR Voyix Corp.",
      "manager_id": "FPA",
      "shares": 5038208,
      "value": 51390000,
      "percentage": 0.69,
      "portfolio_percent": 0.69,
      "reported_price": 10.2,
      "current_price": 6.89,
      "price_change_percent": 0.0,
      "recent_activity": "Add 28.89%",
      "week_52_low": 6.02,
      "week_52_high": 14.67,
      "reporting_date": "",
      "reporting_quarter": "Q2 2026",
      "market_cap": 0.0,
      "pe_ratio": 0.0,
      "dividend_yield": 0.0,
      "price_to_book": 0.0,
      "sector": "",
      "industry": "",
      "data_quality": "Low"
    },
    {
      "symbol": "DELL",
      "company_name": "Dell Technologies Inc.",
      "manager_id": "FPA",
      "shares": 382985,
      "value": 48210000,
      "percentage": 0.65,
      "portfolio_percent": 0.65,
      "reported_price": 125.88,
      "current_price": 208.95,
      "price_change_percent": 0.0,
      "recent_activity": "Reduce 8.49%",
      "week_52_low": 90.42,
      "week_52_high": 221.5,
      "reporting_date": "",
      "reporting_quarter": "Q2 2026",
      "market_cap": 0.0,
      "pe_ratio": 0.0,
      "dividend_yield": 0.0,
      "price_to_book": 0.0,
      "sector": "",
      "industry": "",
      "data_quality": "Low"
    },
    {
      "symbol": "AVTR",
      "company_name": "Avantor Inc.",
      "manager_id": "FPA",
      "shares": 3968620,
      "value": 45480000,
      "percentage": 0.61,
      "portfolio_percent": 0.61,
      "reported_price": 11.46,
      "current_price": 8.1,
      "price_change_percent": 0.0,
      "recent_activity": "Reduce 2.51%",
      "week_52_low": 7.27,
      "week_52_high": 15.93,
      "reporting_date": "",
      "reporting_quarter": "Q2 2026",
      "market_cap": 0.0,
      "pe_ratio": 0.0,
      "dividend_yield": 0.0,
      "price_to_book": 0.0,
      "sector": "",
      "industry": "",
      "data_quality": "Low"
    },
    {
      "symbol": "AVGO",
      "company_name": "Broadcom Inc.",
      "manager_id": "FPA",
      "shares": 86111,
      "value": 29803000,
      "percentage": 0.4,
      "portfolio_percent": 0.4,
      "reported_price": 346.1,
      "current_price": 417.43,
      "price_change_percent": 0.0,
      "recent_activity": "Reduce 24.94%",
      "week_52_low": 194.37,
      "week_52_high": 429.31,
      "reporting_date": "",
      "reporting_quarter": "Q2 2026",
      "market_cap": 0.0,
      "pe_ratio": 0.0,
      "dividend_yield": 0.0,
      "price_to_book": 0.0,
      "sector": "",
      "industry": "",
      "data_quality": "Low"
    },
    {
      "symbol": "GPOR",
      "company_name": "Gulfport Energy Corp.",
      "manager_id": "FPA",
      "shares": 127434,
      "value": 26505000,
      "percentage": 0.36,
      "portfolio_percent": 0.36,
      "reported_price": 207.99,
      "current_price": 192.54,
      "price_change_percent": 0.0,
      "recent_activity": "Reduce 25.83%",
      "week_52_low": 160.95,
      "week_52_high": 225.78,
      "reporting_date": "",
      "reporting_quarter": "Q2 2026",
      "market_cap": 0.0,
      "pe_ratio": 0.0,
      "dividend_yield": 0.0,
      "price_to_book": 0.0,
      "sector": "",
      "industry": "",
      "data_quality": "Low"
    },
    {
      "symbol": "MICC",
      "company_name": "Magnum Ice Cream Co NV",
      "manager_id": "FPA",
      "shares": 1697675,
      "value": 26908000,
      "percentage": 0.36,
      "portfolio_percent": 0.36,
      "reported_price": 15.85,
      "current_price": 14.93,
      "price_change_percent": 0.0,
      "recent_activity": "Buy",
      "week_52_low": 12.94,
      "week_52_high": 19.93,
      "reporting_date": "",
      "reporting_quarter": "Q2 2026",
      "market_cap": 0.0,
      "pe_ratio": 0.0,
      "dividend_yield": 0.0,
      "price_to_book": 0.0,
      "sector": "",
      "industry": "",
      "data_quality": "Low"
    },
    {
      "symbol": "SATS",
      "company_name": "EchoStar Corp.",
      "manager_id": "FPA",
      "shares": 238933,
      "value": 25972000,
      "percentage": 0.35,
      "portfolio_percent": 0.35,
      "reported_price": 108.7,
      "current_price": 123.14,
      "price_change_percent": 0.0,
      "recent_activity": "Reduce 50.31%",
      "week_52_low": 14.9,
      "week_52_high": 137.44,
      "reporting_date": "",
      "reporting_quarter": "Q2 2026",
      "market_cap": 0.0,
      "pe_ratio": 0.0,
      "dividend_yield": 0.0,
      "price_to_book": 0.0,
      "sector": "",
      "industry": "",
      "data_quality": "Low"
    },
    {
      "symbol": "PCG",
      "company_name": "PG&E Corp.",
      "manager_id": "FPA",
      "shares": 1142167,
      "value": 18355000,
      "percentage": 0.25,
      "portfolio_percent": 0.25,
      "reported_price": 16.07,
      "current_price": 16.62,
      "price_change_percent": 0.0,
      "recent_activity": "Add 1.87%",
      "week_52_low": 12.87,
      "week_52_high": 19.1,
      "reporting_date": "",
      "reporting_quarter": "Q2 2026",
      "market_cap": 0.0,
      "pe_ratio": 0.0,
      "dividend_yield": 0.0,
      "price_to_book": 0.0,
      "sector": "",
      "industry": "",
      "data_quality": "Low"
    },
    {
      "symbol": "RUSHA",
      "company_name": "Rush Enterprises Inc.",
      "manager_id": "FPA",
      "shares": 148094,
      "value": 7988000,
      "percentage": 0.11,
      "portfolio_percent": 0.11,
      "reported_price": 53.94,
      "current_price": 74.03,
      "price_change_percent": 0.0,
      "recent_activity": "Reduce 6.91%",
      "week_52_low": 45.38,
      "week_52_high": 76.99,
      "reporting_date": "",
      "reporting_quarter": "Q2 2026",
      "market_cap": 0.0,
      "pe_ratio": 0.0,
      "dividend_yield": 0.0,
      "price_to_book": 0.0,
      "sector": "",
      "industry": "",
      "data_quality": "Low"
    },
    {
      "symbol": "STGW",
      "company_name": "Stagwell Inc.",
      "manager_id": "FPA",
      "shares": 1191918,
      "value": 5828000,
      "percentage": 0.08,
      "portfolio_percent": 0.08,
      "reported_price": 4.89,
      "current_price": 6.27,
      "price_change_percent": 0.0,
      "recent_activity": "",
      "week_52_low": 4.03,
      "week_52_high": 7.52,
      "reporting_date": "",
      "reporting_quarter": "Q2 2026",
      "market_cap": 0.0,
      "pe_ratio": 0.0,
      "dividend_yield": 0.0,
      "price_to_book": 0.0,
      "sector": "",
      "industry": "",
      "data_quality": "Low"
    },
    {
      "symbol": "TDW",
      "company_name": "Tidewater Inc.",
      "manager_id": "FPA",
      "shares": 94961,
      "value": 4796000,
      "percentage": 0.06,
      "portfolio_percent": 0.06,
      "reported_price": 50.5,
      "current_price": 89.33,
      "price_change_percent": 0.0,
      "recent_activity": "",
      "week_52_low": 36.03,
      "week_52_high": 93.13,
      "reporting_date": "",
      "reporting_quarter": "Q2 2026",
      "market_cap": 0.0,
      "pe_ratio": 0.0,
      "dividend_yield": 0.0,
      "price_to_book": 0.0,
      "sector": "",
      "industry": "",
      "data_quality": "Low"
    },
    {
      "symbol": "LAUR",
      "company_name": "Laureate Education Inc.",
      "manager_id": "FPA",
      "shares": 101485,
      "value": 3417000,
      "percentage": 0.05,
      "portfolio_percent": 0.05,
      "reported_price": 33.67,
      "current_price": 30.1,
      "price_change_percent": 0.0,
      "recent_activity": "Reduce 53.02%",
      "week_52_low": 19.71,
      "week_52_high": 37.91,
      "reporting_date": "",
      "reporting_quarter": "Q2 2026",
      "market_cap": 0.0,
      "pe_ratio": 0.0,
      "dividend_yield": 0.0,
      "price_to_book": 0.0,
      "sector": "",
      "industry": "",
      "data_quality": "Low"
    },
    {
      "symbol": "SGOV",
      "company_name": "Ishares 0 3 Month Treasury B",
      "manager_id": "FPA",
      "shares": 40837,
      "value": 4099000,
      "percentage": 0.05,
      "portfolio_percent": 0.05,
      "reported_price": 100.37,
      "current_price": 100.67,
      "price_change_percent": 0.0,
      "recent_activity": "Add 11.66%",
      "week_52_low": 96.8,
      "week_52_high": 100.68,
      "reporting_date": "",
      "reporting_quarter": "Q2 2026",
      "market_cap": 0.0,
      "pe_ratio": 0.0,
      "dividend_yield": 0.0,
      "price_to_book": 0.0,
      "sector": "",
      "industry": "",
      "data_quality": "Low"
    },
    {
      "symbol": "ALGT",
      "company_name": "Allegiant Travel Company",
      "manager_id": "FPA",
      "shares": 34186,
      "value": 2915000,
      "percentage": 0.04,
      "portfolio_percent": 0.04,
      "reported_price": 85.27,
      "current_price": 75.64,
      "price_change_percent": 0.0,
      "recent_activity": "",
      "week_52_low": 42.56,
      "week_52_high": 118.0,
      "reporting_date": "",
      "reporting_quarter": "Q2 2026",
      "market_cap": 0.0,
      "pe_ratio": 0.0,
      "dividend_yield": 0.0,
      "price_to_book": 0.0,
      "sector": "",
      "industry": "",
      "data_quality": "Low"
    },
    {
      "symbol": "MRVI",
      "company_name": "Maravai LifeSciences Holdings Inc.",
      "manager_id": "FPA",
      "shares": 884883,
      "value": 2876000,
      "percentage": 0.04,
      "portfolio_percent": 0.04,
      "reported_price": 3.25,
      "current_price": 3.68,
      "price_change_percent": 0.0,
      "recent_activity": "",
      "week_52_low": 1.95,
      "week_52_high": 4.11,
      "reporting_date": "",
      "reporting_quarter": "Q2 2026",
      "market_cap": 0.0,
      "pe_ratio": 0.0,
      "dividend_yield": 0.0,
      "price_to_book": 0.0,
      "sector": "",
      "industry": "",
      "data_quality": "Low"
    },
    {
      "symbol": "PDLB",
      "company_name": "Ponce Financial Group Inc.",
      "manager_id": "FPA",
      "shares": 181562,
      "value": 2969000,
      "percentage": 0.04,
      "portfolio_percent": 0.04,
      "reported_price": 16.35,
      "current_price": 17.46,
      "price_change_percent": 0.0,
      "recent_activity": "",
      "week_52_low": 12.73,
      "week_52_high": 18.05,
      "reporting_date": "",
      "reporting_quarter": "Q2 2026",
      "market_cap": 0.0,
      "pe_ratio": 0.0,
      "dividend_yield": 0.0,
      "price_to_book": 0.0,
      "sector": "",
      "industry": "",
      "data_quality": "Low"
    },
    {
      "symbol": "VT",
      "company_name": "Vanguard Tot World Stk ETF",
      "manager_id": "FPA",
      "shares": 19743,
      "value": 2785000,
      "percentage": 0.04,
      "portfolio_percent": 0.04,
      "reported_price": 141.06,
      "current_price": 151.2,
      "price_change_percent": 0.0,
      "recent_activity": "Add 9.90%",
      "week_52_low": 114.72,
      "week_52_high": 151.44,
      "reporting_date": "",
      "reporting_quarter": "Q2 2026",
      "market_cap": 0.0,
      "pe_ratio": 0.0,
      "dividend_yield": 0.0,
      "price_to_book": 0.0,
      "sector": "",
      "industry": "",
      "data_quality": "Low"
    },
    {
      "symbol": "DAR",
      "company_name": "Darling Ingredients Inc.",
      "manager_id": "FPA",
      "shares": 52447,
      "value": 1888000,
      "percentage": 0.03,
      "portfolio_percent": 0.03,
      "reported_price": 36.0,
      "current_price": 64.23,
      "price_change_percent": 0.0,
      "recent_activity": "",
      "week_52_low": 29.15,
      "week_52_high": 64.9,
      "reporting_date": "",
      "reporting_quarter": "Q2 2026",
      "market_cap": 0.0,
      "pe_ratio": 0.0,
      "dividend_yield": 0.0,
      "price_to_book": 0.0,
      "sector": "",
      "industry": "",
      "data_quality": "Low"
    },
    {
      "symbol": "OEC",
      "company_name": "Orion SA",
      "manager_id": "FPA",
      "shares": 417388,
      "value": 2204000,
      "percentage": 0.03,
      "portfolio_percent": 0.03,
      "reported_price": 5.28,
      "current_price": 7.52,
      "price_change_percent": 0.0,
      "recent_activity": "",
      "week_52_low": 4.31,
      "week_52_high": 12.34,
      "reporting_date": "",
      "reporting_quarter": "Q2 2026",
      "market_cap": 0.0,
      "pe_ratio": 0.0,
      "dividend_yield": 0.0,
      "price_to_book": 0.0,
      "sector": "",
      "industry": "",
      "data_quality": "Low"
    },
    {
      "symbol": "PBFS",
      "company_name": "Pioneer Bancorp Inc.",
      "manager_id": "FPA",
      "shares": 166974,
      "value": 2251000,
      "percentage": 0.03,
      "portfolio_percent": 0.03,
      "reported_price": 13.48,
      "current_price": 14.23,
      "price_change_percent": 0.0,
      "recent_activity": "",
      "week_52_low": 11.09,
      "week_52_high": 15.18,
      "reporting_date": "",
      "reporting_quarter": "Q2 2026",
      "market_cap": 0.0,
      "pe_ratio": 0.0,
      "dividend_yield": 0.0,
      "price_to_book": 0.0,
      "sector": "",
      "industry": "",
      "data_quality": "Low"
    },
    {
      "symbol": "RSVR",
      "company_name": "Reservoir Media Inc.",
      "manager_id": "FPA",
      "shares": 329066,
      "value": 2491000,
      "percentage": 0.03,
      "portfolio_percent": 0.03,
      "reported_price": 7.57,
      "current_price": 10.06,
      "price_change_percent": 0.0,
      "recent_activity": "",
      "week_52_low": 6.97,
      "week_52_high": 10.32,
      "reporting_date": "",
      "reporting_quarter": "Q2 2026",
      "market_cap": 0.0,
      "pe_ratio": 0.0,
      "dividend_yield": 0.0,
      "price_to_book": 0.0,
      "sector": "",
      "industry": "",
      "data_quality": "Low"
    },
    {
      "symbol": "ASLE",
      "company_name": "Aersale Corp",
      "manager_id": "FPA",
      "shares": 208726,
      "value": 1484000,
      "percentage": 0.02,
      "portfolio_percent": 0.02,
      "reported_price": 7.11,
      "current_price": 6.72,
      "price_change_percent": 0.0,
      "recent_activity": "",
      "week_52_low": 5.56,
      "week_52_high": 9.12,
      "reporting_date": "",
      "reporting_quarter": "Q2 2026",
      "market_cap": 0.0,
      "pe_ratio": 0.0,
      "dividend_yield": 0.0,
      "price_to_book": 0.0,
      "sector": "",
      "industry": "",
      "data_quality": "Low"
    },
    {
      "symbol": "EBC",
      "company_name": "Eastern Bankshares Inc.",
      "manager_id": "FPA",
      "shares": 85883,
      "value": 1583000,
      "percentage": 0.02,
      "portfolio_percent": 0.02,
      "reported_price": 18.43,
      "current_price": 20.23,
      "price_change_percent": 0.0,
      "recent_activity": "",
      "week_52_low": 13.8,
      "week_52_high": 22.42,
      "reporting_date": "",
      "reporting_quarter": "Q2 2026",
      "market_cap": 0.0,
      "pe_ratio": 0.0,
      "dividend_yield": 0.0,
      "price_to_book": 0.0,
      "sector": "",
      "industry": "",
      "data_quality": "Low"
    },
    {
      "symbol": "NFLX",
      "company_name": "Netflix Inc.",
      "manager_id": "FPA",
      "shares": 16400,
      "value": 1538000,
      "percentage": 0.02,
      "portfolio_percent": 0.02,
      "reported_price": 93.78,
      "current_price": 93.61,
      "price_change_percent": 0.0,
      "recent_activity": "",
      "week_52_low": 75.01,
      "week_52_high": 134.12,
      "reporting_date": "",
      "reporting_quarter": "Q2 2026",
      "market_cap": 0.0,
      "pe_ratio": 0.0,
      "dividend_yield": 0.0,
      "price_to_book": 0.0,
      "sector": "",
      "industry": "",
      "data_quality": "Low"
    },
    {
      "symbol": "PARR",
      "company_name": "Par Pacific Holdings",
      "manager_id": "FPA",
      "shares": 43716,
      "value": 1536000,
      "percentage": 0.02,
      "portfolio_percent": 0.02,
      "reported_price": 35.14,
      "current_price": 65.67,
      "price_change_percent": 0.0,
      "recent_activity": "Reduce 21.98%",
      "week_52_low": 14.0,
      "week_52_high": 68.0,
      "reporting_date": "",
      "reporting_quarter": "Q2 2026",
      "market_cap": 0.0,
      "pe_ratio": 0.0,
      "dividend_yield": 0.0,
      "price_to_book": 0.0,
      "sector": "",
      "industry": "",
      "data_quality": "Low"
    },
    {
      "symbol": "UPWK",
      "company_name": "Upwork Inc.",
      "manager_id": "FPA",
      "shares": 57081,
      "value": 1131000,
      "percentage": 0.02,
      "portfolio_percent": 0.02,
      "reported_price": 19.81,
      "current_price": 10.35,
      "price_change_percent": 0.0,
      "recent_activity": "Reduce 45.58%",
      "week_52_low": 10.15,
      "week_52_high": 22.84,
      "reporting_date": "",
      "reporting_quarter": "Q2 2026",
      "market_cap": 0.0,
      "pe_ratio": 0.0,
      "dividend_yield": 0.0,
      "price_to_book": 0.0,
      "sector": "",
      "industry": "",
      "data_quality": "Low"
    },
    {
      "symbol": "HYBB",
      "company_name": "Ishares Bb Rated Corp Bond",
      "manager_id": "FPA",
      "shares": 286,
      "value": 13000,
      "percentage": 0.0,
      "portfolio_percent": 0.0,
      "reported_price": 45.45,
      "current_price": 46.9,
      "price_change_percent": 0.0,
      "recent_activity": "Buy",
      "week_52_low": 43.3,
      "week_52_high": 47.19,
      "reporting_date": "",
      "reporting_quarter": "Q2 2026",
      "market_cap": 0.0,
      "pe_ratio": 0.0,
      "dividend_yield": 0.0,
      "price_to_book": 0.0,
      "sector": "",
      "industry": "",
      "data_quality": "Low"
    },
    {
      "symbol": "UNIT",
      "company_name": "Uniti Group Inc.",
      "manager_id": "FPA",
      "shares": 25235,
      "value": 177000,
      "percentage": 0.0,
      "portfolio_percent": 0.0,
      "reported_price": 7.01,
      "current_price": 11.83,
      "price_change_percent": 0.0,
      "recent_activity": "",
      "week_52_low": 5.3,
      "week_52_high": 12.18,
      "reporting_date": "",
      "reporting_quarter": "Q2 2026",
      "market_cap": 0.0,
      "pe_ratio": 0.0,
      "dividend_yield": 0.0,
      "price_to_book": 0.0,
      "sector": "",
      "industry": "",
      "data_quality": "Low"
    }
  ],
  "timestamp": "2026-05-01T06:59:16.529011",
  "scraped_date": "2026-05-01"
}