{
  "manager_id": "SEQUX",
  "holdings": [
    {
      "symbol": "RYCEF",
      "company_name": "Rolls Royce Holdings plc",
      "manager_id": "SEQUX",
      "shares": 30376735,
      "value": 470883000,
      "percentage": 12.93,
      "portfolio_percent": 12.93,
      "reported_price": 15.5,
      "current_price": 14.35,
      "price_change_percent": 0.0,
      "recent_activity": "Reduce 27.49%",
      "week_52_low": 7.91,
      "week_52_high": 19.15,
      "reporting_date": "May 18, 2018",
      "reporting_quarter": "Q2 2026",
      "market_cap": 0.0,
      "pe_ratio": 0.0,
      "dividend_yield": 0.0,
      "price_to_book": 0.0,
      "sector": "",
      "industry": "",
      "data_quality": "Low"
    },
    {
      "symbol": "GOOGL",
      "company_name": "Alphabet Inc.",
      "manager_id": "SEQUX",
      "shares": 991141,
      "value": 310227000,
      "percentage": 8.52,
      "portfolio_percent": 8.52,
      "reported_price": 313.0,
      "current_price": 287.56,
      "price_change_percent": 0.0,
      "recent_activity": "Reduce 14.23%",
      "week_52_low": 140.04,
      "week_52_high": 348.75,
      "reporting_date": "May 18, 2018",
      "reporting_quarter": "Q2 2026",
      "market_cap": 0.0,
      "pe_ratio": 0.0,
      "dividend_yield": 0.0,
      "price_to_book": 0.0,
      "sector": "",
      "industry": "",
      "data_quality": "Low"
    },
    {
      "symbol": "FWONK",
      "company_name": "Liberty Media Corp Formula One Series C",
      "manager_id": "SEQUX",
      "shares": 2739436,
      "value": 269862000,
      "percentage": 7.41,
      "portfolio_percent": 7.41,
      "reported_price": 98.51,
      "current_price": 85.02,
      "price_change_percent": 0.0,
      "recent_activity": "Reduce 0.16%",
      "week_52_low": 75.26,
      "week_52_high": 109.36,
      "reporting_date": "May 18, 2018",
      "reporting_quarter": "Q2 2026",
      "market_cap": 0.0,
      "pe_ratio": 0.0,
      "dividend_yield": 0.0,
      "price_to_book": 0.0,
      "sector": "",
      "industry": "",
      "data_quality": "Low"
    },
    {
      "symbol": "UMGNF",
      "company_name": "Universal Music Grp NV",
      "manager_id": "SEQUX",
      "shares": 8685297,
      "value": 226901000,
      "percentage": 6.23,
      "portfolio_percent": 6.23,
      "reported_price": 26.12,
      "current_price": 18.55,
      "price_change_percent": 0.0,
      "recent_activity": "Reduce 0.16%",
      "week_52_low": 17.36,
      "week_52_high": 33.49,
      "reporting_date": "May 18, 2018",
      "reporting_quarter": "Q2 2026",
      "market_cap": 0.0,
      "pe_ratio": 0.0,
      "dividend_yield": 0.0,
      "price_to_book": 0.0,
      "sector": "",
      "industry": "",
      "data_quality": "Low"
    },
    {
      "symbol": "ERFSF",
      "company_name": "Eurofins Scientific SE",
      "manager_id": "SEQUX",
      "shares": 2921395,
      "value": 214233000,
      "percentage": 5.88,
      "portfolio_percent": 5.88,
      "reported_price": 73.33,
      "current_price": 70.51,
      "price_change_percent": 0.0,
      "recent_activity": "Reduce 0.16%",
      "week_52_low": 47.99,
      "week_52_high": 86.2,
      "reporting_date": "May 18, 2018",
      "reporting_quarter": "Q2 2026",
      "market_cap": 0.0,
      "pe_ratio": 0.0,
      "dividend_yield": 0.0,
      "price_to_book": 0.0,
      "sector": "",
      "industry": "",
      "data_quality": "Low"
    },
    {
      "symbol": "COF",
      "company_name": "Capital One Financial",
      "manager_id": "SEQUX",
      "shares": 826743,
      "value": 200369000,
      "percentage": 5.5,
      "portfolio_percent": 5.5,
      "reported_price": 242.36,
      "current_price": 182.43,
      "price_change_percent": 0.0,
      "recent_activity": "Reduce 0.16%",
      "week_52_low": 141.3,
      "week_52_high": 258.65,
      "reporting_date": "May 18, 2018",
      "reporting_quarter": "Q2 2026",
      "market_cap": 0.0,
      "pe_ratio": 0.0,
      "dividend_yield": 0.0,
      "price_to_book": 0.0,
      "sector": "",
      "industry": "",
      "data_quality": "Low"
    },
    {
      "symbol": "CNSWF",
      "company_name": "Constellation Software Inc.",
      "manager_id": "SEQUX",
      "shares": 82980,
      "value": 199592000,
      "percentage": 5.48,
      "portfolio_percent": 5.48,
      "reported_price": 2405.3,
      "current_price": 1702.03,
      "price_change_percent": 0.0,
      "recent_activity": "Reduce 0.16%",
      "week_52_low": 1611.78,
      "week_52_high": 3992.39,
      "reporting_date": "May 18, 2018",
      "reporting_quarter": "Q2 2026",
      "market_cap": 0.0,
      "pe_ratio": 0.0,
      "dividend_yield": 0.0,
      "price_to_book": 0.0,
      "sector": "",
      "industry": "",
      "data_quality": "Low"
    },
    {
      "symbol": "ELV",
      "company_name": "Elevance Health Inc.",
      "manager_id": "SEQUX",
      "shares": 532467,
      "value": 186656000,
      "percentage": 5.13,
      "portfolio_percent": 5.13,
      "reported_price": 350.55,
      "current_price": 292.75,
      "price_change_percent": 0.0,
      "recent_activity": "Reduce 0.16%",
      "week_52_low": 269.17,
      "week_52_high": 449.16,
      "reporting_date": "May 18, 2018",
      "reporting_quarter": "Q2 2026",
      "market_cap": 0.0,
      "pe_ratio": 0.0,
      "dividend_yield": 0.0,
      "price_to_book": 0.0,
      "sector": "",
      "industry": "",
      "data_quality": "Low"
    },
    {
      "symbol": "SCHW",
      "company_name": "Charles Schwab Corp.",
      "manager_id": "SEQUX",
      "shares": 1671788,
      "value": 167028000,
      "percentage": 4.59,
      "portfolio_percent": 4.59,
      "reported_price": 99.91,
      "current_price": 93.98,
      "price_change_percent": 0.0,
      "recent_activity": "Reduce 27.54%",
      "week_52_low": 65.08,
      "week_52_high": 107.14,
      "reporting_date": "May 18, 2018",
      "reporting_quarter": "Q2 2026",
      "market_cap": 0.0,
      "pe_ratio": 0.0,
      "dividend_yield": 0.0,
      "price_to_book": 0.0,
      "sector": "",
      "industry": "",
      "data_quality": "Low"
    },
    {
      "symbol": "ICE",
      "company_name": "Intercontinental Exchange Inc.",
      "manager_id": "SEQUX",
      "shares": 1015750,
      "value": 164511000,
      "percentage": 4.52,
      "portfolio_percent": 4.52,
      "reported_price": 161.96,
      "current_price": 157.28,
      "price_change_percent": 0.0,
      "recent_activity": "Reduce 0.16%",
      "week_52_low": 142.28,
      "week_52_high": 187.65,
      "reporting_date": "May 18, 2018",
      "reporting_quarter": "Q2 2026",
      "market_cap": 0.0,
      "pe_ratio": 0.0,
      "dividend_yield": 0.0,
      "price_to_book": 0.0,
      "sector": "",
      "industry": "",
      "data_quality": "Low"
    },
    {
      "symbol": "TSM",
      "company_name": "Taiwan Semiconductor S.A.",
      "manager_id": "SEQUX",
      "shares": 497379,
      "value": 151149000,
      "percentage": 4.15,
      "portfolio_percent": 4.15,
      "reported_price": 303.89,
      "current_price": 337.95,
      "price_change_percent": 0.0,
      "recent_activity": "Reduce 26.75%",
      "week_52_low": 132.62,
      "week_52_high": 389.11,
      "reporting_date": "May 18, 2018",
      "reporting_quarter": "Q2 2026",
      "market_cap": 0.0,
      "pe_ratio": 0.0,
      "dividend_yield": 0.0,
      "price_to_book": 0.0,
      "sector": "",
      "industry": "",
      "data_quality": "Low"
    },
    {
      "symbol": "ASHTF",
      "company_name": "Ashtead Group plc",
      "manager_id": "SEQUX",
      "shares": 2179199,
      "value": 149399000,
      "percentage": 4.1,
      "portfolio_percent": 4.1,
      "reported_price": 68.56,
      "current_price": 72.36,
      "price_change_percent": 0.0,
      "recent_activity": "Reduce 0.16%",
      "week_52_low": 44.8,
      "week_52_high": 76.61,
      "reporting_date": "May 18, 2018",
      "reporting_quarter": "Q2 2026",
      "market_cap": 0.0,
      "pe_ratio": 0.0,
      "dividend_yield": 0.0,
      "price_to_book": 0.0,
      "sector": "",
      "industry": "",
      "data_quality": "Low"
    },
    {
      "symbol": "SAP",
      "company_name": "SAP SE",
      "manager_id": "SEQUX",
      "shares": 574255,
      "value": 140519000,
      "percentage": 3.86,
      "portfolio_percent": 3.86,
      "reported_price": 244.7,
      "current_price": 171.21,
      "price_change_percent": 0.0,
      "recent_activity": "Reduce 0.16%",
      "week_52_low": 163.77,
      "week_52_high": 313.28,
      "reporting_date": "May 18, 2018",
      "reporting_quarter": "Q2 2026",
      "market_cap": 0.0,
      "pe_ratio": 0.0,
      "dividend_yield": 0.0,
      "price_to_book": 0.0,
      "sector": "",
      "industry": "",
      "data_quality": "Low"
    },
    {
      "symbol": "ICLR",
      "company_name": "ICON plc",
      "manager_id": "SEQUX",
      "shares": 631186,
      "value": 115015000,
      "percentage": 3.16,
      "portfolio_percent": 3.16,
      "reported_price": 182.22,
      "current_price": 110.66,
      "price_change_percent": 0.0,
      "recent_activity": "Add 0.11%",
      "week_52_low": 66.57,
      "week_52_high": 211.0,
      "reporting_date": "May 18, 2018",
      "reporting_quarter": "Q2 2026",
      "market_cap": 0.0,
      "pe_ratio": 0.0,
      "dividend_yield": 0.0,
      "price_to_book": 0.0,
      "sector": "",
      "industry": "",
      "data_quality": "Low"
    },
    {
      "symbol": "MSA",
      "company_name": "MSA Safety Inc.",
      "manager_id": "SEQUX",
      "shares": 672227,
      "value": 107650000,
      "percentage": 2.96,
      "portfolio_percent": 2.96,
      "reported_price": 160.14,
      "current_price": 163.95,
      "price_change_percent": 0.0,
      "recent_activity": "Buy",
      "week_52_low": 126.28,
      "week_52_high": 208.37,
      "reporting_date": "May 18, 2018",
      "reporting_quarter": "Q2 2026",
      "market_cap": 0.0,
      "pe_ratio": 0.0,
      "dividend_yield": 0.0,
      "price_to_book": 0.0,
      "sector": "",
      "industry": "",
      "data_quality": "Low"
    },
    {
      "symbol": "ACN",
      "company_name": "Accenture",
      "manager_id": "SEQUX",
      "shares": 352334,
      "value": 94531000,
      "percentage": 2.6,
      "portfolio_percent": 2.6,
      "reported_price": 268.3,
      "current_price": 198.29,
      "price_change_percent": 0.0,
      "recent_activity": "Buy",
      "week_52_low": 187.0,
      "week_52_high": 320.13,
      "reporting_date": "May 18, 2018",
      "reporting_quarter": "Q2 2026",
      "market_cap": 0.0,
      "pe_ratio": 0.0,
      "dividend_yield": 0.0,
      "price_to_book": 0.0,
      "sector": "",
      "industry": "",
      "data_quality": "Low"
    },
    {
      "symbol": "CACC",
      "company_name": "Credit Acceptance Corp.",
      "manager_id": "SEQUX",
      "shares": 205750,
      "value": 91242000,
      "percentage": 2.51,
      "portfolio_percent": 2.51,
      "reported_price": 443.46,
      "current_price": 423.46,
      "price_change_percent": 0.0,
      "recent_activity": "Reduce 5.82%",
      "week_52_low": 401.9,
      "week_52_high": 549.75,
      "reporting_date": "May 18, 2018",
      "reporting_quarter": "Q2 2026",
      "market_cap": 0.0,
      "pe_ratio": 0.0,
      "dividend_yield": 0.0,
      "price_to_book": 0.0,
      "sector": "",
      "industry": "",
      "data_quality": "Low"
    },
    {
      "symbol": "UNH",
      "company_name": "United Health Group Inc.",
      "manager_id": "SEQUX",
      "shares": 277001,
      "value": 91441000,
      "percentage": 2.51,
      "portfolio_percent": 2.51,
      "reported_price": 330.11,
      "current_price": 270.59,
      "price_change_percent": 0.0,
      "recent_activity": "Reduce 0.16%",
      "week_52_low": 229.79,
      "week_52_high": 589.73,
      "reporting_date": "May 18, 2018",
      "reporting_quarter": "Q2 2026",
      "market_cap": 0.0,
      "pe_ratio": 0.0,
      "dividend_yield": 0.0,
      "price_to_book": 0.0,
      "sector": "",
      "industry": "",
      "data_quality": "Low"
    },
    {
      "symbol": "ALGN",
      "company_name": "Align Technology Inc.",
      "manager_id": "SEQUX",
      "shares": 454963,
      "value": 71042000,
      "percentage": 1.95,
      "portfolio_percent": 1.95,
      "reported_price": 156.15,
      "current_price": 171.43,
      "price_change_percent": 0.0,
      "recent_activity": "Buy",
      "week_52_low": 122.0,
      "week_52_high": 208.31,
      "reporting_date": "May 18, 2018",
      "reporting_quarter": "Q2 2026",
      "market_cap": 0.0,
      "pe_ratio": 0.0,
      "dividend_yield": 0.0,
      "price_to_book": 0.0,
      "sector": "",
      "industry": "",
      "data_quality": "Low"
    },
    {
      "symbol": "META",
      "company_name": "Meta Platforms Inc.",
      "manager_id": "SEQUX",
      "shares": 70138,
      "value": 46297000,
      "percentage": 1.27,
      "portfolio_percent": 1.27,
      "reported_price": 660.08,
      "current_price": 572.13,
      "price_change_percent": 0.0,
      "recent_activity": "Reduce 0.16%",
      "week_52_low": 478.31,
      "week_52_high": 794.38,
      "reporting_date": "May 18, 2018",
      "reporting_quarter": "Q2 2026",
      "market_cap": 0.0,
      "pe_ratio": 0.0,
      "dividend_yield": 0.0,
      "price_to_book": 0.0,
      "sector": "",
      "industry": "",
      "data_quality": "Low"
    },
    {
      "symbol": "BRK.B",
      "company_name": "Berkshire Hathaway CL B",
      "manager_id": "SEQUX",
      "shares": 78269,
      "value": 39342000,
      "percentage": 1.08,
      "portfolio_percent": 1.08,
      "reported_price": 502.65,
      "current_price": 479.2,
      "price_change_percent": 0.0,
      "recent_activity": "Reduce 0.16%",
      "week_52_low": 455.19,
      "week_52_high": 542.07,
      "reporting_date": "May 18, 2018",
      "reporting_quarter": "Q2 2026",
      "market_cap": 0.0,
      "pe_ratio": 0.0,
      "dividend_yield": 0.0,
      "price_to_book": 0.0,
      "sector": "",
      "industry": "",
      "data_quality": "Low"
    },
    {
      "symbol": "AMTM",
      "company_name": "Amentum Holdings Inc.",
      "manager_id": "SEQUX",
      "shares": 1012960,
      "value": 29376000,
      "percentage": 0.81,
      "portfolio_percent": 0.81,
      "reported_price": 29.0,
      "current_price": 26.08,
      "price_change_percent": 0.0,
      "recent_activity": "Reduce 0.16%",
      "week_52_low": 16.01,
      "week_52_high": 38.11,
      "reporting_date": "May 18, 2018",
      "reporting_quarter": "Q2 2026",
      "market_cap": 0.0,
      "pe_ratio": 0.0,
      "dividend_yield": 0.0,
      "price_to_book": 0.0,
      "sector": "",
      "industry": "",
      "data_quality": "Low"
    },
    {
      "symbol": "CHTR",
      "company_name": "Charter Communications",
      "manager_id": "SEQUX",
      "shares": 136469,
      "value": 28488000,
      "percentage": 0.78,
      "portfolio_percent": 0.78,
      "reported_price": 208.75,
      "current_price": 215.88,
      "price_change_percent": 0.0,
      "recent_activity": "Reduce 0.16%",
      "week_52_low": 180.38,
      "week_52_high": 437.06,
      "reporting_date": "May 18, 2018",
      "reporting_quarter": "Q2 2026",
      "market_cap": 0.0,
      "pe_ratio": 0.0,
      "dividend_yield": 0.0,
      "price_to_book": 0.0,
      "sector": "",
      "industry": "",
      "data_quality": "Low"
    },
    {
      "symbol": "LBRDK",
      "company_name": "Liberty Broadband Corp. CL C",
      "manager_id": "SEQUX",
      "shares": 582797,
      "value": 28324000,
      "percentage": 0.78,
      "portfolio_percent": 0.78,
      "reported_price": 48.6,
      "current_price": 50.3,
      "price_change_percent": 0.0,
      "recent_activity": "Reduce 0.16%",
      "week_52_low": 42.1,
      "week_52_high": 97.16,
      "reporting_date": "May 18, 2018",
      "reporting_quarter": "Q2 2026",
      "market_cap": 0.0,
      "pe_ratio": 0.0,
      "dividend_yield": 0.0,
      "price_to_book": 0.0,
      "sector": "",
      "industry": "",
      "data_quality": "Low"
    },
    {
      "symbol": "RYCEY",
      "company_name": "Rolls Royce Holdings Sp ADR",
      "manager_id": "SEQUX",
      "shares": 1148165,
      "value": 18049000,
      "percentage": 0.5,
      "portfolio_percent": 0.5,
      "reported_price": 15.72,
      "current_price": 14.57,
      "price_change_percent": 0.0,
      "recent_activity": "Buy",
      "week_52_low": 7.91,
      "week_52_high": 18.98,
      "reporting_date": "May 18, 2018",
      "reporting_quarter": "Q2 2026",
      "market_cap": 0.0,
      "pe_ratio": 0.0,
      "dividend_yield": 0.0,
      "price_to_book": 0.0,
      "sector": "",
      "industry": "",
      "data_quality": "Low"
    },
    {
      "symbol": "LBRDA",
      "company_name": "Liberty Broadband Corp. CL A",
      "manager_id": "SEQUX",
      "shares": 340216,
      "value": 16426000,
      "percentage": 0.45,
      "portfolio_percent": 0.45,
      "reported_price": 48.28,
      "current_price": 50.22,
      "price_change_percent": 0.0,
      "recent_activity": "Reduce 0.16%",
      "week_52_low": 42.05,
      "week_52_high": 95.93,
      "reporting_date": "May 18, 2018",
      "reporting_quarter": "Q2 2026",
      "market_cap": 0.0,
      "pe_ratio": 0.0,
      "dividend_yield": 0.0,
      "price_to_book": 0.0,
      "sector": "",
      "industry": "",
      "data_quality": "Low"
    },
    {
      "symbol": "GLIBK",
      "company_name": "GCI Liberty Inc. Series C",
      "manager_id": "SEQUX",
      "shares": 181122,
      "value": 6740000,
      "percentage": 0.19,
      "portfolio_percent": 0.19,
      "reported_price": 37.21,
      "current_price": 37.21,
      "price_change_percent": 0.0,
      "recent_activity": "Add 55.14%",
      "week_52_low": 28.11,
      "week_52_high": 41.18,
      "reporting_date": "May 18, 2018",
      "reporting_quarter": "Q2 2026",
      "market_cap": 0.0,
      "pe_ratio": 0.0,
      "dividend_yield": 0.0,
      "price_to_book": 0.0,
      "sector": "",
      "industry": "",
      "data_quality": "Low"
    },
    {
      "symbol": "FWONA",
      "company_name": "Liberty Media Corp Formula One Series A",
      "manager_id": "SEQUX",
      "shares": 42201,
      "value": 3772000,
      "percentage": 0.1,
      "portfolio_percent": 0.1,
      "reported_price": 89.38,
      "current_price": 78.08,
      "price_change_percent": 0.0,
      "recent_activity": "Reduce 0.16%",
      "week_52_low": 68.0,
      "week_52_high": 99.52,
      "reporting_date": "May 18, 2018",
      "reporting_quarter": "Q2 2026",
      "market_cap": 0.0,
      "pe_ratio": 0.0,
      "dividend_yield": 0.0,
      "price_to_book": 0.0,
      "sector": "",
      "industry": "",
      "data_quality": "Low"
    },
    {
      "symbol": "GLBAV",
      "company_name": "GCI Liberty Inc. Series A",
      "manager_id": "SEQUX",
      "shares": 68043,
      "value": 2509000,
      "percentage": 0.07,
      "portfolio_percent": 0.07,
      "reported_price": 36.87,
      "current_price": 0.0,
      "price_change_percent": 0.0,
      "recent_activity": "Reduce 0.16%",
      "week_52_low": 0.0,
      "week_52_high": 0.0,
      "reporting_date": "May 18, 2018",
      "reporting_quarter": "Q2 2026",
      "market_cap": 0.0,
      "pe_ratio": 0.0,
      "dividend_yield": 0.0,
      "price_to_book": 0.0,
      "sector": "",
      "industry": "",
      "data_quality": "Low"
    }
  ],
  "timestamp": "2026-04-01T06:39:56.856204",
  "scraped_date": "2026-04-01"
}